np_nwb/__init__.py
np_nwb/dynamic_routing_dev.py
np_nwb/ephys_utils.py
np_nwb/interfaces.py
np_nwb/utils.py
np_nwb/database/__init__.py
np_nwb/database/base.py
np_nwb/database/json_db.py
np_nwb/database/validated.py
np_nwb/dynamic_routing/__init__.py
np_nwb/dynamic_routing/licks.py
np_nwb/dynamic_routing/running.py
np_nwb/dynamic_routing/utils.py
np_nwb/init_with_metadata/__init__.py
np_nwb/init_with_metadata/__main__.py
np_nwb/init_with_metadata/from_np_session.py
np_nwb/metadata/__init__.py
np_nwb/metadata/__main__.py
np_nwb/metadata/from_np_session.py
np_nwb/scripts/__init__.py
np_nwb/scripts/generate_dynamic_routing_pilot_ecephys.py
np_nwb/scripts/generate_sound_latencies.py
np_nwb/trials/DRtask.py
np_nwb/trials/RFtrials.py
np_nwb/trials/__init__.py
np_nwb/trials/property_dict.py
np_nwb/videos/__init__.py
np_nwb/videos/videos.py
np_nwb-0.1.2.dist-info/METADATA
np_nwb-0.1.2.dist-info/WHEEL
np_nwb-0.1.2.dist-info/top_level.txt
np_nwb-0.1.2.dist-info/RECORD
