Metadata-Version: 2.1
Name: np-nwb
Version: 0.1.2
Summary: Tools for quickly generating `.nwb` files from non-standard Mindscope Neuropixels experiments.
Author-email: arjunsridhar12345 <arjun.sridhar@alleninstitute.org>, bjhardcastle <ben.hardcastle@alleninstitute.org>, mochic <chrism@alleninstitute.org>
License: MIT
Requires-Python: >=3.9
Requires-Dist: pynwb
Requires-Dist: ndx-events (>=0.2.0)
Requires-Dist: ndx-sound (>=0.2.0)
Provides-Extra: db
Requires-Dist: pydantic (<2.0.0) ; extra == 'db'
Requires-Dist: universal-pathlib (>=0.0.23) ; extra == 'db'
Requires-Dist: aiohttp (>=3.7.4) ; extra == 'db'
Requires-Dist: requests (>=2.31.0) ; extra == 'db'
Requires-Dist: fsspec (>=2023.6.0) ; extra == 'db'
Requires-Dist: s3fs (>=0.6.0) ; extra == 'db'
Requires-Dist: pandas ; extra == 'db'
Provides-Extra: dev
Requires-Dist: np-nwb[onsite] ; extra == 'dev'
Requires-Dist: mypy ; extra == 'dev'
Requires-Dist: ruff ; extra == 'dev'
Requires-Dist: pydantic (<2.0) ; extra == 'dev'
Provides-Extra: offsite
Requires-Dist: np-nwb[packaging] ; extra == 'offsite'
Provides-Extra: onsite
Requires-Dist: np-nwb[packaging] ; extra == 'onsite'
Requires-Dist: np-session ; extra == 'onsite'
Requires-Dist: np-eyetracking (>=0.1.1) ; extra == 'onsite'
Requires-Dist: np-nwb-trials (==0.3.0) ; extra == 'onsite'
Requires-Dist: np-tools (>=0.1.16) ; extra == 'onsite'
Provides-Extra: packaging
Requires-Dist: np-nwb[db] ; extra == 'packaging'
Requires-Dist: scipy (>=1.9.3) ; extra == 'packaging'
Requires-Dist: numba (>=0.57.1) ; extra == 'packaging'
